{
  "runId": "e7a18420-95b5-4dcc-bb23-271b7ac1f6a0",
  "state": "completed",
  "startedAt": "2026-03-20T07:20:42.266Z",
  "totalCompanies": 468,
  "savedCount": 0,
  "failedCount": 1,
  "progress": {
    "index": 100,
    "total": 468
  },
  "lastCompany": "Direct Bazaar Pvt. Ltd.",
  "lastTasks": [
    "description"
  ],
  "lastMessage": "[12:51:01 pm] ✗   FAILED: No JSON in response: \"{",
  "exitCode": 0,
  "finishedAt": "2026-03-20T07:21:04.444Z",
  "lastLogLine": "╚══════════════════════════════════════════════════════════╝\\n"
}